fast_c2pa_core.libs/libcrypto-ee446395.so.3
fast_c2pa_core.libs/libssl-4194be63.so.3
fast_c2pa_core/__init__.py
fast_c2pa_core/fast_c2pa_core.cpython-312-x86_64-linux-gnu.so
fast_c2pa_python-0.1.6.dist-info/METADATA
fast_c2pa_python-0.1.6.dist-info/WHEEL
fast_c2pa_python-0.1.6.dist-info/licenses/LICENSE
fast_c2pa_python/__init__.py
fast_c2pa_python-0.1.6.dist-info/RECORD
