Metadata-Version: 2.4
Name: fast-c2pa-python
Version: 0.1.6
Classifier: Development Status :: 4 - Beta
Classifier: Intended Audience :: Developers
Classifier: Programming Language :: Rust
Classifier: Programming Language :: Python :: Implementation :: CPython
Classifier: Programming Language :: Python :: 3.11
Classifier: Programming Language :: Python :: 3.12
Classifier: License :: OSI Approved :: MIT License
Classifier: License :: OSI Approved :: Apache Software License
Classifier: Operating System :: POSIX :: Linux
License-File: LICENSE
Summary: Fast Python library for reading C2PA metadata using PyO3 bindings to c2pa-rs
Keywords: c2pa,metadata,python,bindings
Author: Sightengine <info@sightengine.com>
Author-email: Sightengine <info@sightengine.com>
License: MIT OR Apache-2.0
Requires-Python: >=3.11
